flask_jsonschema_validator/__init__.py
flask_jsonschema_validator/jsonschemavalidator.py
test/__init__.py
test/test_flask_jsonschema_validator.py
flask_jsonschema_validator-0.0.4.dist-info/LICENSE.txt
flask_jsonschema_validator-0.0.4.dist-info/METADATA
flask_jsonschema_validator-0.0.4.dist-info/WHEEL
flask_jsonschema_validator-0.0.4.dist-info/top_level.txt
flask_jsonschema_validator-0.0.4.dist-info/RECORD
