Metadata-Version: 2.1
Name: flask-jsonschema-validator
Version: 0.0.4
Summary: Validate Flask JSON request data with schema files and route decorators
Home-page: https://gitlab.com/vector.kerr/flask-jsonschema-validator
Author: Daniel 'Vector' Kerr
Author-email: vector@vector.id.au
License: MIT
Keywords: flask jsonschema validator validation json schema
Platform: UNKNOWN
Classifier: Programming Language :: Python :: 2
Classifier: License :: OSI Approved :: MIT License
Classifier: Operating System :: OS Independent
